{
    "components": [
        "CR",
        "FE"
    ],
    "phases": [
        "(CR,FE)",
        "LIQUID",
        "CR0.5FE0.5_136_TP30",
        "FE,NI_225_CF4"
    ],
    "conditions": {
        "P": 101325,
        "T": [

            1805.68,
            1802.06,
            1798.82,
            1795.95,
            1793.43,
            1791.26,
            1789.4,
            1787.85,
            1786.6,
            1785.63,
            1784.92,
            1784.46,
            1784.23,
            1784.22,
            1784.42,
            1784.81,
            1785.37,
            1788.84,
            1793.14,
            1798.54,
            1805.28,
            1813.65,
            1823.89,
            1836.28,
            1851.08,
            1868.55,
            1888.96,
            1912.56,
            1939.63,
            1970.42,
            2005.2,
            2044.23,
            2087.7799999999997,
            573.0,
            583.637,
            593.943,
            603.923,
            613.5830000000001,
            622.928,
            631.963,
            640.694,
            649.127,
            657.267,
            665.1179999999999,
            672.688,
            679.981,
            687.002,
            693.758,
            700.2529999999999,
            706.4929999999999,
            712.483,
            744.71,
            777.2280000000001,
            809.747,
            841.979,
            873.632,
            904.418,
            934.047,
            962.229,
            988.674,
            1013.092,
            1035.1950000000002,
            1054.692,
            1071.2939999999999,
            1084.711,
            1094.653,
            1100.8310000000001,
            1102.954,
            1100.906,
            1094.9360000000001,
            1085.306,
            1072.278,
            1056.114,
            1037.076,
            1015.426,
            991.426,
            965.337,
            937.422,
            907.943,
            877.162,
            845.34,
            812.74,
            779.623,
            746.252,
            712.8879999999999,
            712.483,
            706.581,
            699.9739999999999,
            693.079,
            685.909,
            678.4739999999999,
            670.788,
            662.861,
            654.706,
            646.335,
            637.759,
            628.991,
            620.0409999999999,
            610.923,
            601.648,
            592.2280000000001,
            582.675,
            573.0,
            1173.933,
            1164.2820000000002,
            1155.827,
            1148.49,
            1142.192,
            1136.853,
            1132.394,
            1128.7350000000001,
            1125.798,
            1123.5030000000002,
            1121.772,
            1120.524,
            1119.6799999999998,
            1119.162,
            1118.8899999999999,
            1118.7849999999999,
            1118.768,
            1122.306,
            1132.51,
            1148.763,
            1170.451,
            1196.955,
            1227.662,
            1261.954,
            1299.22,
            1338.83,
            1380.18,
            1422.66,
            1465.64,
            1508.51,
            1550.65,
            1591.45,
            1630.3
        ]
    },
    "output": "ZPF",
    "broadcast_conditions": false,
    "values":
			[
			[["(CR,FE)",["FE"],[0.9862439999999999]],["LIQUID",["FE"],[0.9730172453987734]]],
			[["(CR,FE)",["FE"],[0.972692]],["LIQUID",["FE"],[0.9479197573964497]]],
			[["(CR,FE)",["FE"],[0.9593349999999999]],["LIQUID",["FE"],[0.9245553529411754]]],
			[["(CR,FE)",["FE"],[0.9461660000000001]],["LIQUID",["FE"],[0.9029433373493981]]],
			[["(CR,FE)",["FE"],[0.93318]],["LIQUID",["FE"],[0.8830186809815953]]],
			[["(CR,FE)",["FE"],[0.920368]],["LIQUID",["FE"],[0.864892176470589]]],
			[["(CR,FE)",["FE"],[0.9077249999999999]],["LIQUID",["FE"],[0.8484557379310352]]],
			[["(CR,FE)",["FE"],[0.895242]],["LIQUID",["FE"],[0.8338597591240864]]],
			[["(CR,FE)",["FE"],[0.8829130000000001]],["LIQUID",["FE"],[0.821340671874999]]],
			[["(CR,FE)",["FE"],[0.8707309999999999]],["LIQUID",["FE"],[0.8110534745762724]]],
			[["(CR,FE)",["FE"],[0.8586879999999999]],["LIQUID",["FE"],[0.8031694661016963]]],
			[["(CR,FE)",["FE"],[0.846779]],["LIQUID",["FE"],[0.7976667735849066]]],
			[["(CR,FE)",["FE"],[0.834996]],["LIQUID",["FE"],[0.7948533962264156]]],
			[["(CR,FE)",["FE"],[0.823331]],["LIQUID",["FE"],[0.7947310754716987]]],
			[["(CR,FE)",["FE"],[0.8117789999999999]],["LIQUID",["FE"],[0.797177490566039]]],
			[["(CR,FE)",["FE"],[0.800331]],["LIQUID",["FE"],[0.801948]]],
			[["(CR,FE)",["FE"],[0.7889820000000001]],["LIQUID",["FE"],[0.773944268456377]]],
			[["(CR,FE)",["FE"],[0.734772]],["LIQUID",["FE"],[0.7417338187919473]]],
			[["(CR,FE)",["FE"],[0.683672]],["LIQUID",["FE"],[0.7121146980023496]]],
			[["(CR,FE)",["FE"],[0.635257]],["LIQUID",["FE"],[0.6786894091743122]]],
			[["(CR,FE)",["FE"],[0.589097]],["LIQUID",["FE"],[0.6467040899082568]]],
			[["(CR,FE)",["FE"],[0.544767]],["LIQUID",["FE"],[0.6112284760820039]]],
			[["(CR,FE)",["FE"],[0.501839]],["LIQUID",["FE"],[0.5732194397905754]]],
			[["(CR,FE)",["FE"],[0.459887]],["LIQUID",["FE"],[0.5336987454188481]]],
			[["(CR,FE)",["FE"],[0.41848100000000005]],["LIQUID",["FE"],[0.492468245949074]]],
			[["(CR,FE)",["FE"],[0.377197]],["LIQUID",["FE"],[0.44887685034013614]]],
			[["(CR,FE)",["FE"],[0.335606]],["LIQUID",["FE"],[0.40304622766570597]]],
			[["(CR,FE)",["FE"],[0.293281]],["LIQUID",["FE"],[0.3549650687500002]]],
			[["(CR,FE)",["FE"],[0.24979500000000002]],["LIQUID",["FE"],[0.30436750545759844]]],
			[["(CR,FE)",["FE"],[0.20472100000000001]],["LIQUID",["FE"],[0.25135017326732645]]],
			[["(CR,FE)",["FE"],[0.157632]],["LIQUID",["FE"],[0.19518238797213044]]],
			[["(CR,FE)",["FE"],[0.1081]],["LIQUID",["FE"],[0.13508274103019532]]],
			[["(CR,FE)",["FE"],[0.0556984]],["LIQUID",["FE"],[0.07049466207598386]]],
			[["(CR,FE)",["FE"],[0.034693100000000004]],["(CR,FE)",["FE"],[0.034693100000000004]]],
			[["(CR,FE)",["FE"],[0.0386049]],["(CR,FE)",["FE"],[0.0386049]]],
			[["(CR,FE)",["FE"],[0.0426024]],["(CR,FE)",["FE"],[0.0426024]]],
			[["(CR,FE)",["FE"],[0.0466841]],["(CR,FE)",["FE"],[0.0466841]]],
			[["(CR,FE)",["FE"],[0.0508487]],["(CR,FE)",["FE"],[0.0508487]]],
			[["(CR,FE)",["FE"],[0.0550948]],["(CR,FE)",["FE"],[0.0550948]]],
			[["(CR,FE)",["FE"],[0.059421]],["(CR,FE)",["FE"],[0.059421]]],
			[["(CR,FE)",["FE"],[0.0638258]],["(CR,FE)",["FE"],[0.0638258]]],
			[["(CR,FE)",["FE"],[0.068308]],["(CR,FE)",["FE"],[0.068308]]],
			[["(CR,FE)",["FE"],[0.072866]],["(CR,FE)",["FE"],[0.072866]]],
			[["(CR,FE)",["FE"],[0.0774985]],["(CR,FE)",["FE"],[0.0774985]]],
			[["(CR,FE)",["FE"],[0.0822042]],["(CR,FE)",["FE"],[0.0822042]]],
			[["(CR,FE)",["FE"],[0.0869815]],["(CR,FE)",["FE"],[0.0869815]]],
			[["(CR,FE)",["FE"],[0.0918291]],["(CR,FE)",["FE"],[0.0918291]]],
			[["(CR,FE)",["FE"],[0.09674569999999999]],["(CR,FE)",["FE"],[0.09674569999999999]]],
			[["(CR,FE)",["FE"],[0.10173]],["(CR,FE)",["FE"],[0.10173]]],
			[["(CR,FE)",["FE"],[0.10678000000000001]],["(CR,FE)",["FE"],[0.10678000000000001]]],
			[["(CR,FE)",["FE"],[0.11189500000000001]],["CR0.5FE0.5_136_TP30",["FE"],[0.509722]]],
			[["(CR,FE)",["FE"],[0.133054]],["CR0.5FE0.5_136_TP30",["FE"],[0.5054572752146781]]],
			[["(CR,FE)",["FE"],[0.154978]],["CR0.5FE0.5_136_TP30",["FE"],[0.5033752950218277]]],
			[["(CR,FE)",["FE"],[0.17759799999999998]],["CR0.5FE0.5_136_TP30",["FE"],[0.5020202395374267]]],
			[["(CR,FE)",["FE"],[0.20084700000000003]],["CR0.5FE0.5_136_TP30",["FE"],[0.5011331418061031]]],
			[["(CR,FE)",["FE"],[0.22465800000000002]],["CR0.5FE0.5_136_TP30",["FE"],[0.5006645382240077]]],
			[["(CR,FE)",["FE"],[0.248964]],["CR0.5FE0.5_136_TP30",["FE"],[0.5005947185742763]]],
			[["(CR,FE)",["FE"],[0.273697]],["CR0.5FE0.5_136_TP30",["FE"],[0.5009145139183697]]],
			[["(CR,FE)",["FE"],[0.29879100000000003]],["CR0.5FE0.5_136_TP30",["FE"],[0.5016562804293772]]],
			[["(CR,FE)",["FE"],[0.32417700000000005]],["CR0.5FE0.5_136_TP30",["FE"],[0.5028785675409315]]],
			[["(CR,FE)",["FE"],[0.349789]],["CR0.5FE0.5_136_TP30",["FE"],[0.5045392823399787]]],
			[["(CR,FE)",["FE"],[0.37555900000000003]],["CR0.5FE0.5_136_TP30",["FE"],[0.5066416757953618]]],
			[["(CR,FE)",["FE"],[0.40142000000000005]],["CR0.5FE0.5_136_TP30",["FE"],[0.5091707846703476]]],
			[["(CR,FE)",["FE"],[0.427305]],["CR0.5FE0.5_136_TP30",["FE"],[0.5121240657913052]]],
			[["(CR,FE)",["FE"],[0.453147]],["CR0.5FE0.5_136_TP30",["FE"],[0.5159270350813304]]],
			[["(CR,FE)",["FE"],[0.478877]],["CR0.5FE0.5_136_TP30",["FE"],[0.5204144327179292]]],
			[["(CR,FE)",["FE"],[0.5044299999999999]],["CR0.5FE0.5_136_TP30",["FE"],[0.5263427977005202]]],
			[["(CR,FE)",["FE"],[0.529737]],["CR0.5FE0.5_136_TP30",["FE"],[null]]],
			[["(CR,FE)",["FE"],[0.558208]],["CR0.5FE0.5_136_TP30",["FE"],[0.5327939815934789]]],
			[["(CR,FE)",["FE"],[0.586507]],["CR0.5FE0.5_136_TP30",["FE"],[0.5392216824749907]]],
			[["(CR,FE)",["FE"],[0.614541]],["CR0.5FE0.5_136_TP30",["FE"],[0.5439260623592176]]],
			[["(CR,FE)",["FE"],[0.642217]],["CR0.5FE0.5_136_TP30",["FE"],[0.5476120519264966]]],
			[["(CR,FE)",["FE"],[0.669442]],["CR0.5FE0.5_136_TP30",["FE"],[0.5503268575969485]]],
			[["(CR,FE)",["FE"],[0.696124]],["CR0.5FE0.5_136_TP30",["FE"],[0.5524889328864173]]],
			[["(CR,FE)",["FE"],[0.722169]],["CR0.5FE0.5_136_TP30",["FE"],[0.5540129630681818]]],
			[["(CR,FE)",["FE"],[0.7474850000000001]],["CR0.5FE0.5_136_TP30",["FE"],[0.554866718312944]]],
			[["(CR,FE)",["FE"],[0.7719790000000001]],["CR0.5FE0.5_136_TP30",["FE"],[0.554905899565095]]],
			[["(CR,FE)",["FE"],[0.7955580000000001]],["CR0.5FE0.5_136_TP30",["FE"],[0.5542170931115963]]],
			[["(CR,FE)",["FE"],[0.818128]],["CR0.5FE0.5_136_TP30",["FE"],[0.5528073550389877]]],
			[["(CR,FE)",["FE"],[0.8395980000000001]],["CR0.5FE0.5_136_TP30",["FE"],[0.5506036248252477]]],
			[["(CR,FE)",["FE"],[0.8598739999999999]],["CR0.5FE0.5_136_TP30",["FE"],[0.5474962772038355]]],
			[["(CR,FE)",["FE"],[0.878864]],["CR0.5FE0.5_136_TP30",["FE"],[0.5432979363962289]]],
			[["(CR,FE)",["FE"],[0.896473]],["CR0.5FE0.5_136_TP30",["FE"],[0.5376534619003519]]],
			[["(CR,FE)",["FE"],[0.912611]],["CR0.5FE0.5_136_TP30",["FE"],[0.5296517274901285]]],
			[["(CR,FE)",["FE"],[0.927183]],["(CR,FE)",["FE"],[0.927183]]],
			[["(CR,FE)",["FE"],[0.9273981823370857]],["(CR,FE)",["FE"],[0.9273981823370857]]],
			[["(CR,FE)",["FE"],[0.930534]],["(CR,FE)",["FE"],[0.930534]]],
			[["(CR,FE)",["FE"],[0.933729]],["(CR,FE)",["FE"],[0.933729]]],
			[["(CR,FE)",["FE"],[0.9367740000000001]],["(CR,FE)",["FE"],[0.9367740000000001]]],
			[["(CR,FE)",["FE"],[0.9396760000000001]],["(CR,FE)",["FE"],[0.9396760000000001]]],
			[["(CR,FE)",["FE"],[0.9424410000000001]],["(CR,FE)",["FE"],[0.9424410000000001]]],
			[["(CR,FE)",["FE"],[0.9450749999999999]],["(CR,FE)",["FE"],[0.9450749999999999]]],
			[["(CR,FE)",["FE"],[0.947585]],["(CR,FE)",["FE"],[0.947585]]],
			[["(CR,FE)",["FE"],[0.949976]],["(CR,FE)",["FE"],[0.949976]]],
			[["(CR,FE)",["FE"],[0.952255]],["(CR,FE)",["FE"],[0.952255]]],
			[["(CR,FE)",["FE"],[0.954429]],["(CR,FE)",["FE"],[0.954429]]],
			[["(CR,FE)",["FE"],[0.956503]],["(CR,FE)",["FE"],[0.956503]]],
			[["(CR,FE)",["FE"],[0.958484]],["(CR,FE)",["FE"],[0.958484]]],
			[["(CR,FE)",["FE"],[0.960379]],["(CR,FE)",["FE"],[0.960379]]],
			[["(CR,FE)",["FE"],[0.962192]],["(CR,FE)",["FE"],[0.962192]]],
			[["(CR,FE)",["FE"],[0.9639319999999999]],["(CR,FE)",["FE"],[0.9639319999999999]]],
			[["(CR,FE)",["FE"],[0.965603]],["(CR,FE)",["FE"],[0.965603]]],
			[["(CR,FE)",["FE"],[0.967213]],["(CR,FE)",["FE"],[0.967213]]],
			[["(CR,FE)",["FE"],[0.995441]],["(CR,FE)",["FE"],[null]]],
			[["(CR,FE)",["FE"],[0.990555]],["(CR,FE)",["FE"],[0.990555]]],
			[["(CR,FE)",["FE"],[0.985411]],["(CR,FE)",["FE"],[0.985411]]],
			[["(CR,FE)",["FE"],[0.980079]],["(CR,FE)",["FE"],[0.980079]]],
			[["(CR,FE)",["FE"],[0.974628]],["(CR,FE)",["FE"],[0.974628]]],
			[["(CR,FE)",["FE"],[0.969127]],["(CR,FE)",["FE"],[0.969127]]],
			[["(CR,FE)",["FE"],[0.9636450000000001]],["(CR,FE)",["FE"],[0.9636450000000001]]],
			[["(CR,FE)",["FE"],[0.9582510000000001]],["(CR,FE)",["FE"],[0.9582510000000001]]],
			[["(CR,FE)",["FE"],[0.9530150000000001]],["(CR,FE)",["FE"],[0.9530150000000001]]],
			[["(CR,FE)",["FE"],[0.948005]],["(CR,FE)",["FE"],[0.948005]]],
			[["(CR,FE)",["FE"],[0.943291]],["(CR,FE)",["FE"],[0.943291]]],
			[["(CR,FE)",["FE"],[0.9389409999999999]],["(CR,FE)",["FE"],[0.9389409999999999]]],
			[["(CR,FE)",["FE"],[0.935026]],["(CR,FE)",["FE"],[0.935026]]],
			[["(CR,FE)",["FE"],[0.931613]],["(CR,FE)",["FE"],[0.931613]]],
			[["(CR,FE)",["FE"],[0.9287730000000001]],["(CR,FE)",["FE"],[0.9287730000000001]]],
			[["(CR,FE)",["FE"],[0.926574]],["FE,NI_225_CF4",["FE"],[0.9253543957597163]]],
			[["(CR,FE)",["FE"],[0.925086]],["FE,NI_225_CF4",["FE"],[0.925086]]],
			[["(CR,FE)",["FE"],[0.9105599999999999]],["FE,NI_225_CF4",["FE"],[0.9143494993588099]]],
			[["(CR,FE)",["FE"],[0.897332]],["FE,NI_225_CF4",["FE"],[0.904277043322912]]],
			[["(CR,FE)",["FE"],[0.8856149999999999]],["FE,NI_225_CF4",["FE"],[0.8958984077226606]]],
			[["(CR,FE)",["FE"],[0.875624]],["FE,NI_225_CF4",["FE"],[0.8891534020395155]]],
			[["(CR,FE)",["FE"],[0.867573]],["FE,NI_225_CF4",["FE"],[0.8841069019525508]]],
			[["(CR,FE)",["FE"],[0.861674]],["FE,NI_225_CF4",["FE"],[0.8808393509385744]]],
			[["(CR,FE)",["FE"],[0.858142]],["FE,NI_225_CF4",["FE"],[0.8794382213677561]]],
			[["(CR,FE)",["FE"],[0.8571899999999999]],["FE,NI_225_CF4",["FE"],[0.8799969989284621]]],
			[["(CR,FE)",["FE"],[0.859032]],["FE,NI_225_CF4",["FE"],[0.8826181096023278]]],
			[["(CR,FE)",["FE"],[0.8638819999999999]],["FE,NI_225_CF4",["FE"],[0.8874167453562191]]],
			[["(CR,FE)",["FE"],[0.8719540000000001]],["FE,NI_225_CF4",["FE"],[0.8945284839758476]]],
			[["(CR,FE)",["FE"],[0.88346]],["FE,NI_225_CF4",["FE"],[0.9041120242763772]]],
			[["(CR,FE)",["FE"],[0.898616]],["FE,NI_225_CF4",["FE"],[0.9163686265520535]]],
			[["(CR,FE)",["FE"],[0.9176340000000001]],["FE,NI_225_CF4",["FE"],[0.9315664788346614]]],
			[["(CR,FE)",["FE"],[0.940728]],["FE,NI_225_CF4",["FE"],[0.9500963560626161]]],
			[["(CR,FE)",["FE"],[0.968112]],["FE,NI_225_CF4",["FE"],[0.9725666657963447]]]],
	"reference": "C900765"
}